{"IIkz0KmuxFC0zf7ydvFfSA==":"img-5680-2000x1333.jpg","57zxBdIRjMGbAsEg9rZShA==":"dsc-154-2000x1333.jpg","TUS99hk/BsvnXAAGel9rwQ==":"mbr-1920x1280.jpg","InlWUSkWiE75crJGbokn+w==":"fb%20cover-1484x755.png","pa5Dkwo/T1qgW/t0h+fQvA==":"background5.jpg","b9nL/YGInftUuDc7YdGkGg==":"dsc-210-2000x1333.jpg","ofwenkhtyDtk1bfNjvatNw==":"logo_main-262x262.png","sT80Y4RCGNBrSInGgrjIuA==":"background3.jpg","FK5uSwIrdGv3k4f/8R4FWA==":"block_&_hit-1046x1395.png","UAc7kepzJPkrSn4uqTRvmw==":"background4.jpg","nqCzamNF9WvXWYZ5pKcUHw==":"vb-1046x1511.png","U4HmiJMOIaJ5GKywIZyFPA==":"28_07-20-1046x1510.png","tiI8j82mWlbbFVecFmhYBA==":"1-1-676x686.jpg","+Hs8phtXSk79h+Nb2ePGEQ==":"1-676x659.jpg","py9zo1vZVgxoRPMva1UMHw==":"1-676x667.jpg","Ev6nk8kirCAGfivKfOMdOQ==":"et-1046x1395.png","HXDE1+XTKVG7YHpbxtpEng==":"et-1046x1510.png","DTkfx/ERQyxJ2feU8UJqGA==":"1-1046x1404.png","NvZ51JfflksNgY7JgANETw==":"2-1046x1404.png","8cRID5wfsZWrFxbaPa5SWg==":"3-1466x962.png","5kuHRXK23ut7As/hkx9zZg==":"_raj4992-2000x1125.jpg"}